cidr_list/__init__.py
cidr_list/cli.py
cidr_list-0.1.1.dist-info/DESCRIPTION.rst
cidr_list-0.1.1.dist-info/METADATA
cidr_list-0.1.1.dist-info/RECORD
cidr_list-0.1.1.dist-info/WHEEL
cidr_list-0.1.1.dist-info/entry_points.txt
cidr_list-0.1.1.dist-info/metadata.json
cidr_list-0.1.1.dist-info/pbr.json
cidr_list-0.1.1.dist-info/top_level.txt
